loop_to_recursion/__init__.py
loop_to_recursion/loop_to_recursion.py
loop_to_recursion-0.1.1.dist-info/LICENSE
loop_to_recursion-0.1.1.dist-info/METADATA
loop_to_recursion-0.1.1.dist-info/WHEEL
loop_to_recursion-0.1.1.dist-info/entry_points.txt
loop_to_recursion-0.1.1.dist-info/RECORD
