Metadata-Version: 2.3
Name: loop-to-recursion
Version: 0.1.1
Summary: Convert the given Python code into an equivalent code without for/while loops
License: MIT
Author: Yuki Kobayashi
Author-email: drsuaimqjgar@gmail.com
Requires-Python: >=3.13
Classifier: License :: OSI Approved :: MIT License
Classifier: Programming Language :: Python :: 3
Classifier: Programming Language :: Python :: 3.13
Project-URL: source, https://github.com/koyuki7w/loop-to-recursion
